pyziggy/__init__.py
pyziggy/__main__.py
pyziggy/broadcasters.py
pyziggy/cli.py
pyziggy/code_line.py
pyziggy/devices_client.py
pyziggy/generator.py
pyziggy/message_loop.py
pyziggy/mqtt_client.py
pyziggy/parameters.py
pyziggy/parser.py
pyziggy/py.typed
pyziggy/run.py
pyziggy/workarounds.py
pyziggy/device_bases/__init__.py
pyziggy/device_bases/_device_base_requirements.py
pyziggy/device_bases/_device_base_rules.py
pyziggy/testing/__init__.py
pyziggy/testing/connection_ascii_art.py
pyziggy/testing/message_event.py
pyziggy/testing/mock_mqtt_clients.py
pyziggy/util/__init__.py
pyziggy/util/_util.py
pyziggy-0.9.3.dist-info/licenses/LICENSE.md
pyziggy-0.9.3.dist-info/METADATA
pyziggy-0.9.3.dist-info/WHEEL
pyziggy-0.9.3.dist-info/entry_points.txt
pyziggy-0.9.3.dist-info/top_level.txt
pyziggy-0.9.3.dist-info/RECORD
