Metadata-Version: 2.4
Name: pyziggy
Version: 0.9.3
Summary: Autogenerates Python classes for communicating with Zigbee2MQTT
Author-email: Attila Szarvas <attila.szarvas@gmail.com>
License:                     GNU GENERAL PUBLIC LICENSE
Classifier: Programming Language :: Python :: 3
Classifier: Operating System :: OS Independent
Requires-Python: <3.15,>=3.12
License-File: LICENSE.md
Requires-Dist: paho-mqtt==2.1.0
Requires-Dist: toml==0.10.2
Requires-Dist: types-toml==0.10.8.20240310
Requires-Dist: mypy==1.15.0
Requires-Dist: Flask==3.1.0
Requires-Dist: black==25.1.0
Dynamic: license-file
